{"date": ["3", "2020"], "102356": {"Store Total": 26647.0, "RETAIL, PRODUCE": 14302.0, "RETAIL, MEAT AND DELI": 765.0, "RETAIL, MIX FOOD": 11565.0, "RETAIL, NON FOOD": 15.0}, "130550": {"Store Total": 15310.0, "RETAIL, PRODUCE": 6765.0, "RETAIL, MEAT AND DELI": 1335.0, "RETAIL, MIX FOOD": 6130.0, "RETAIL, NON FOOD": 105.0, "RETAIL, DAIRY": 975.0}, "147832": {"Store Total": 20235.0, "RETAIL, PRODUCE": 13185.0, "RETAIL, MEAT AND DELI": 1240.0, "RETAIL, MIX FOOD": 5315.0, "RETAIL, NON FOOD": 145.0, "RETAIL, DAIRY": 350.0}, "159886": {"Store Total": 15575.0, "RETAIL, PRODUCE": 9112.0, "RETAIL, MEAT AND DELI": 1160.0, "RETAIL, MIX FOOD": 5143.0, "RETAIL, NON FOOD": 160.0}, "226547": {"Store Total": 26540.0, "RETAIL, PRODUCE": 17845.0, "RETAIL, MEAT AND DELI": 521.0, "RETAIL, MIX FOOD": 7954.0, "RETAIL, DAIRY": 220.0}, "5569866": {"Store Total": 33017.0, "RETAIL, PRODUCE": 20166.0, "RETAIL, MIX FOOD": 11561.0, "RETAIL, NON FOOD": 1290.0}, "631314": {"Store Total": 21116.0, "RETAIL, PRODUCE": 8068.0, "RETAIL, MEAT AND DELI": 25.0, "RETAIL, MIX FOOD": 13023.0}, "631569": {"Store Total": 16925.0, "RETAIL, PRODUCE": 9090.0, "RETAIL, MEAT AND DELI": 1140.0, "RETAIL, MIX FOOD": 4885.0, "RETAIL, NON FOOD": 1565.0, "RETAIL, DAIRY": 245.0}, "631636": {"Store Total": 15031.0, "RETAIL, PRODUCE": 7364.0, "RETAIL, MEAT AND DELI": 2486.0, "RETAIL, MIX FOOD": 3326.0, "RETAIL, DAIRY": 1855.0}, "6338555": {"Store Total": 8670.0, "RETAIL, PRODUCE": 3520.0, "RETAIL, MEAT AND DELI": 675.0, "RETAIL, MIX FOOD": 4475.0}, "66223344": {"Store Total": 23478.0, "RETAIL, PRODUCE": 11115.0, "RETAIL, MEAT AND DELI": 355.0, "RETAIL, MIX FOOD": 12008.0}}