{"date": ["9", "2019"], "4000": {"Store Total": 2742.0, "RETAIL, PRODUCE": 35.0, "RETAIL, MEAT AND DELI": 577.0, "RETAIL, MIX FOOD": 1304.0, "RETAIL, NON FOOD": 749.0, "RETAIL, DAIRY": 77.0}, "4002": {"Store Total": 945.0, "RETAIL, PRODUCE": 230.0, "RETAIL, MEAT AND DELI": 210.0, "RETAIL, MIX FOOD": 260.0, "RETAIL, DAIRY": 245.0}, "4003": {"Store Total": 2989.0, "RETAIL, PRODUCE": 1063.0, "RETAIL, MIX FOOD": 1668.0, "RETAIL, DAIRY": 258.0}, "4010": {"Store Total": 2645.0, "RETAIL, MIX FOOD": 2645.0}, "4011": {"Store Total": 1321.0, "RETAIL, MEAT AND DELI": 770.0, "RETAIL, MIX FOOD": 551.0}, "4012": {"Store Total": 567.0, "RETAIL, MIX FOOD": 567.0}, "4013": {"Store Total": 658.0, "RETAIL, MEAT AND DELI": 469.0, "RETAIL, MIX FOOD": 189.0}, "4015": {"Store Total": 2855.0, "RETAIL, PRODUCE": 839.0, "RETAIL, MEAT AND DELI": 947.0, "RETAIL, MIX FOOD": 1069.0}}